canadafire.cpython-38-darwin.so
canadafire-1.1.0.dist-info/METADATA
canadafire-1.1.0.dist-info/WHEEL
canadafire-1.1.0.dist-info/top_level.txt
canadafire-1.1.0.dist-info/RECORD
